multi_factory/__init__.py
multi_factory/base.py
multi_factory/errors.py
multi_factory/json_to_domain.py
multi_factory/meta.py
multi_factory/py.typed
multi_factory/types.py
multi_factory/utils.py
multi_factory-0.2.1.dist-info/LICENSE
multi_factory-0.2.1.dist-info/METADATA
multi_factory-0.2.1.dist-info/WHEEL
multi_factory-0.2.1.dist-info/RECORD
