Metadata-Version: 2.1
Name: multi-factory
Version: 0.2.1
Summary: Define a single factory to generate the same data in multiple formats
Home-page: https://github.com/Danthewaann/multi-factory
License: MIT
Keywords: python,factory,multiple,testing,fixtures,marshmallow
Author: Danthewaann
Author-email: danielcrblack@gmail.com
Requires-Python: >=3.10,<3.14
Classifier: Development Status :: 3 - Alpha
Classifier: License :: OSI Approved :: MIT License
Classifier: Operating System :: MacOS :: MacOS X
Classifier: Operating System :: POSIX :: Linux
Classifier: Programming Language :: Python :: 3
Classifier: Programming Language :: Python :: 3.10
Classifier: Programming Language :: Python :: 3.11
Classifier: Programming Language :: Python :: 3.12
Classifier: Programming Language :: Python :: 3.13
Requires-Dist: factory-boy (>=3.3.0)
Requires-Dist: marshmallow (>=3.18.0)
Project-URL: Repository, https://github.com/Danthewaann/multi-factory
